Workbook

Sheet Raw Data 
A1: Date | B1: Medicine | C1: Category | D1: Supplier | E1: Purchase Price | F1: Selling Price | G1: Quantity Sold | H1: Current Stock | I1: Reorder Level | J1: Expiry Date
A2: 46023 | B2: Ibuprofen 400mg | C2: Analgesic | D2: CarePlus Pharma | E2: 1.85 | F2: 2.51 | G2: 18 | H2: 15 | I2: 35 | J2: 46868
A3: 46024 | B3: Loperamide 2mg | C3: Gastrointestinal | D3: Medico Supply Co. | E3: 1.15 | F3: 1.95 | G3: 4 | H3: 40 | I3: 15 | J3: 46431
A4: 46024 | B4: Loratadine 10mg | C4: Allergy | D4: CarePlus Pharma | E4: 0.97 | F4: 1.61 | G4: 16 | H4: 12 | I4: 20 | J4: 46502
A5: 46025 | B5: Ferrous Sulfate 325mg | C5: Supplements | D5: Nile Medical Trading | E5: 1.57 | F5: 2.3 | G5: 13 | H5: 16 | I5: 20 | J5: 46754
A6: 46026 | B6: Metformin 500mg | C6: Diabetes | D6: Nile Medical Trading | E6: 1.76 | F6: 2.82 | G6: 18 | H6: 56 | I6: 35 | J6: 46479
A7: 46027 | B7: Timolol Eye Drops | C7: Ophthalmic | D7: Nile Medical Trading | E7: 3.03 | F7: 4.37 | G7: 3 | H7: 8 | I7: 15 | J7: 46755
A8: 46027 | B8: Diclofenac 50mg | C8: Analgesic | D8: PrimeMed Supplies | E8: 1.54 | F8: 2.5 | G8: 15 | H8: 84 | I8: 35 | J8: 46765
A9: 46027 | B9: Ibuprofen 400mg | C9: Analgesic | D9: PrimeMed Supplies | E9: 1.85 | F9: 2.51 | G9: 16 | H9: 80 | I9: 35 | J9: 46572
A10: 46028 | B10: Cefixime 200mg | C10: Antibiotic | D10: Nile Medical Trading | E10: 3.92 | F10: 5.92 | G10: 13 | H10: 6 | I10: 15 | J10: 46594
A11: 46028 | B11: Atorvastatin 20mg | C11: Cardiovascular | D11: PrimeMed Supplies | E11: 2.89 | F11: 4.44 | G11: 24 | H11: 61 | I11: 20 | J11: 46331
A12: 46028 | B12: Loperamide 2mg | C12: Gastrointestinal | D12: Wellness Distribution | E12: 1.15 | F12: 1.95 | G12: 4 | H12: 5 | I12: 15 | J12: 46609
A13: 46029 | B13: Ibuprofen 400mg | C13: Analgesic | D13: PrimeMed Supplies | E13: 1.85 | F13: 2.51 | G13: 12 | H13: 49 | I13: 35 | J13: 46753
... A501: 46295 | B501: Diclofenac 50mg | C501: Analgesic | D501: CarePlus Pharma | E501: 1.54 | F501: 2.5 | G501: 19 | H501: 50 | I501: 35 | J501: 47007

Sheet Inventory Sales
A1: Medicine | B1: Category | C1: Current Stock | D1: Reorder Level | E1: Stock Status | F1: Stock Difference | G1: Quantity Sold | H1: Purchase Price | I1: Total Purchase Cost | J1: Selling Price | K1: Total Sales Revenue | L1: Profit Per Unit | M1: Total Profit | N1: Profit Margin % | O1: Inventory Value | P1: Reorder Quantity | Q1: Sales Contribution %
A2: Ibuprofen 400mg | B2: =VLOOKUP(A2, 'Raw Data '!B2:C501, 2, FALSE) -> Analgesic | C2: =LOOKUP(2,1/('Raw Data '!$B$2:$B$1000=A2), 'Raw Data '!$H$2:$H$1000) -> 111 | D2: =VLOOKUP(A2, 'Raw Data '!$B$2:$I$501, 8, FALSE) -> 35 | E2: =_xlfn.IFS(C2>D2, "Sufficient Stock", C2=0, "Out Of Stock", C2<=D2, "Reorder Soon" ) -> Sufficient Stock | F2: =SUM(C2-D2) -> 76 | G2: =SUMIF(Table1[Medicine], Table2[[#This Row],[Medicine]],Table1[Quantity Sold]) -> 375 | H2: =VLOOKUP(A2,'Raw Data '!B2:E501, 4, FALSE) -> 1.85 | I2: =SUM(G2*H2) -> 693.75 | J2: =VLOOKUP(A2,'Raw Data '!B2:F501, 5, FALSE) -> 2.51 | K2: =SUM(G2*J2) -> 941.25 | L2: =SUM(J2-H2) -> 0.66 | M2: =SUM(G2*L2) -> 247.5 | N2: =IFERROR(M2/K2, 0) -> 0.26294821 | O2: =SUM(C2*H2) -> 205.35 | P2: =MAX(D2-C2, 0) -> 0 | Q2: =IFERROR(K2/SUM($K$2:$K$31),0) -> 0.041138063
A3: Loperamide 2mg | B3: =VLOOKUP(A3, 'Raw Data '!B3:C502, 2, FALSE) -> Gastrointestinal | C3: =LOOKUP(2,1/('Raw Data '!$B$2:$B$1000=A3), 'Raw Data '!$H$2:$H$1000) -> 18 | D3: =VLOOKUP(A3, 'Raw Data '!$B$2:$I$501, 8, FALSE) -> 15 | E3: =_xlfn.IFS(C3>D3, "Sufficient Stock", C3=0, "Out Of Stock", C3<=D3, "Reorder Soon" ) -> Sufficient Stock | F3: =SUM(C3-D3) -> 3 | G3: =SUMIF(Table1[Medicine], Table2[[#This Row],[Medicine]],Table1[Quantity Sold]) -> 128 | H3: =VLOOKUP(A3,'Raw Data '!B3:E502, 4, FALSE) -> 1.15 | I3: =SUM(G3*H3) -> 147.2 | J3: =VLOOKUP(A3,'Raw Data '!B3:F502, 5, FALSE) -> 1.95 | K3: =SUM(G3*J3) -> 249.6 | L3: =SUM(J3-H3) -> 0.8 | M3: =SUM(G3*L3) -> 102.4 | N3: =IFERROR(M3/K3, 0) -> 0.41025641 | O3: =SUM(C3*H3) -> 20.7 | P3: =MAX(D3-C3, 0) -> 0 | Q3: =IFERROR(K3/SUM($K$2:$K$31),0) -> 0.010908962
A4: Loratadine 10mg | B4: =VLOOKUP(A4, 'Raw Data '!B4:C503, 2, FALSE) -> Allergy | C4: =LOOKUP(2,1/('Raw Data '!$B$2:$B$1000=A4), 'Raw Data '!$H$2:$H$1000) -> 61 | D4: =VLOOKUP(A4, 'Raw Data '!$B$2:$I$501, 8, FALSE) -> 20 | E4: =_xlfn.IFS(C4>D4, "Sufficient Stock", C4=0, "Out Of Stock", C4<=D4, "Reorder Soon" ) -> Sufficient Stock | F4: =SUM(C4-D4) -> 41 | G4: =SUMIF(Table1[Medicine], Table2[[#This Row],[Medicine]],Table1[Quantity Sold]) -> 182 | H4: =VLOOKUP(A4,'Raw Data '!B4:E503, 4, FALSE) -> 0.97 | I4: =SUM(G4*H4) -> 176.54 | J4: =VLOOKUP(A4,'Raw Data '!B4:F503, 5, FALSE) -> 1.61 | K4: =SUM(G4*J4) -> 293.02 | L4: =SUM(J4-H4) -> 0.64 | M4: =SUM(G4*L4) -> 116.48 | N4: =IFERROR(M4/K4, 0) -> 0.39751553 | O4: =SUM(C4*H4) -> 59.17 | P4: =MAX(D4-C4, 0) -> 0 | Q4: =IFERROR(K4/SUM($K$2:$K$31),0) -> 0.012806667
A5: Ferrous Sulfate 325mg | B5: =VLOOKUP(A5, 'Raw Data '!B5:C504, 2, FALSE) -> Supplements | C5: =LOOKUP(2,1/('Raw Data '!$B$2:$B$1000=A5), 'Raw Data '!$H$2:$H$1000) -> 23 | D5: =VLOOKUP(A5, 'Raw Data '!$B$2:$I$501, 8, FALSE) -> 20 | E5: =_xlfn.IFS(C5>D5, "Sufficient Stock", C5=0, "Out Of Stock", C5<=D5, "Reorder Soon" ) -> Sufficient Stock | F5: =SUM(C5-D5) -> 3 | G5: =SUMIF(Table1[Medicine], Table2[[#This Row],[Medicine]],Table1[Quantity Sold]) -> 165 | H5: =VLOOKUP(A5,'Raw Data '!B5:E504, 4, FALSE) -> 1.57 | I5: =SUM(G5*H5) -> 259.05 | J5: =VLOOKUP(A5,'Raw Data '!B5:F504, 5, FALSE) -> 2.3 | K5: =SUM(G5*J5) -> 379.5 | L5: =SUM(J5-H5) -> 0.73 | M5: =SUM(G5*L5) -> 120.45 | N5: =IFERROR(M5/K5, 0) -> 0.3173913 | O5: =SUM(C5*H5) -> 36.11 | P5: =MAX(D5-C5, 0) -> 0 | Q5: =IFERROR(K5/SUM($K$2:$K$31),0) -> 0.016586343
A6: Metformin 500mg | B6: =VLOOKUP(A6, 'Raw Data '!B6:C505, 2, FALSE) -> Diabetes | C6: =LOOKUP(2,1/('Raw Data '!$B$2:$B$1000=A6), 'Raw Data '!$H$2:$H$1000) -> 22 | D6: =VLOOKUP(A6, 'Raw Data '!$B$2:$I$501, 8, FALSE) -> 35 | E6: =_xlfn.IFS(C6>D6, "Sufficient Stock", C6=0, "Out Of Stock", C6<=D6, "Reorder Soon" ) -> Reorder Soon | F6: =SUM(C6-D6) -> -13 | G6: =SUMIF(Table1[Medicine], Table2[[#This Row],[Medicine]],Table1[Quantity Sold]) -> 352 | H6: =VLOOKUP(A6,'Raw Data '!B6:E505, 4, FALSE) -> 1.76 | I6: =SUM(G6*H6) -> 619.52 | J6: =VLOOKUP(A6,'Raw Data '!B6:F505, 5, FALSE) -> 2.82 | K6: =SUM(G6*J6) -> 992.64 | L6: =SUM(J6-H6) -> 1.06 | M6: =SUM(G6*L6) -> 373.12 | N6: =IFERROR(M6/K6, 0) -> 0.37588652 | O6: =SUM(C6*H6) -> 38.72 | P6: =MAX(D6-C6, 0) -> 13 | Q6: =IFERROR(K6/SUM($K$2:$K$31),0) -> 0.043384103
A7: Timolol Eye Drops | B7: =VLOOKUP(A7, 'Raw Data '!B7:C506, 2, FALSE) -> Ophthalmic | C7: =LOOKUP(2,1/('Raw Data '!$B$2:$B$1000=A7), 'Raw Data '!$H$2:$H$1000) -> 20 | D7: =VLOOKUP(A7, 'Raw Data '!$B$2:$I$501, 8, FALSE) -> 15 | E7: =_xlfn.IFS(C7>D7, "Sufficient Stock", C7=0, "Out Of Stock", C7<=D7, "Reorder Soon" ) -> Sufficient Stock | F7: =SUM(C7-D7) -> 5 | G7: =SUMIF(Table1[Medicine], Table2[[#This Row],[Medicine]],Table1[Quantity Sold]) -> 66 | H7: =VLOOKUP(A7,'Raw Data '!B7:E506, 4, FALSE) -> 3.03 | I7: =SUM(G7*H7) -> 199.98 | J7: =VLOOKUP(A7,'Raw Data '!B7:F506, 5, FALSE) -> 4.37 | K7: =SUM(G7*J7) -> 288.42 | L7: =SUM(J7-H7) -> 1.34 | M7: =SUM(G7*L7) -> 88.44 | N7: =IFERROR(M7/K7, 0) -> 0.30663616 | O7: =SUM(C7*H7) -> 60.6 | P7: =MAX(D7-C7, 0) -> 0 | Q7: =IFERROR(K7/SUM($K$2:$K$31),0) -> 0.01260562
A8: Diclofenac 50mg | B8: =VLOOKUP(A8, 'Raw Data '!B8:C507, 2, FALSE) -> Analgesic | C8: =LOOKUP(2,1/('Raw Data '!$B$2:$B$1000=A8), 'Raw Data '!$H$2:$H$1000) -> 50 | D8: =VLOOKUP(A8, 'Raw Data '!$B$2:$I$501, 8, FALSE) -> 35 | E8: =_xlfn.IFS(C8>D8, "Sufficient Stock", C8=0, "Out Of Stock", C8<=D8, "Reorder Soon" ) -> Sufficient Stock | F8: =SUM(C8-D8) -> 15 | G8: =SUMIF(Table1[Medicine], Table2[[#This Row],[Medicine]],Table1[Quantity Sold]) -> 377 | H8: =VLOOKUP(A8,'Raw Data '!B8:E507, 4, FALSE) -> 1.54 | I8: =SUM(G8*H8) -> 580.58 | J8: =VLOOKUP(A8,'Raw Data '!B8:F507, 5, FALSE) -> 2.5 | K8: =SUM(G8*J8) -> 942.5 | L8: =SUM(J8-H8) -> 0.96 | M8: =SUM(G8*L8) -> 361.92 | N8: =IFERROR(M8/K8, 0) -> 0.384 | O8: =SUM(C8*H8) -> 77 | P8: =MAX(D8-C8, 0) -> 0 | Q8: =IFERROR(K8/SUM($K$2:$K$31),0) -> 0.041192696
A9: Cefixime 200mg | B9: =VLOOKUP(A9, 'Raw Data '!B9:C508, 2, FALSE) -> Antibiotic | C9: =LOOKUP(2,1/('Raw Data '!$B$2:$B$1000=A9), 'Raw Data '!$H$2:$H$1000) -> 9 | D9: =VLOOKUP(A9, 'Raw Data '!$B$2:$I$501, 8, FALSE) -> 15 | E9: =_xlfn.IFS(C9>D9, "Sufficient Stock", C9=0, "Out Of Stock", C9<=D9, "Reorder Soon" ) -> Reorder Soon | F9: =SUM(C9-D9) -> -6 | G9: =SUMIF(Table1[Medicine], Table2[[#This Row],[Medicine]],Table1[Quantity Sold]) -> 122 | H9: =VLOOKUP(A9,'Raw Data '!B9:E508, 4, FALSE) -> 3.92 | I9: =SUM(G9*H9) -> 478.24 | J9: =VLOOKUP(A9,'Raw Data '!B9:F508, 5, FALSE) -> 5.92 | K9: =SUM(G9*J9) -> 722.24 | L9: =SUM(J9-H9) -> 2 | M9: =SUM(G9*L9) -> 244 | N9: =IFERROR(M9/K9, 0) -> 0.33783784 | O9: =SUM(C9*H9) -> 35.28 | P9: =MAX(D9-C9, 0) -> 6 | Q9: =IFERROR(K9/SUM($K$2:$K$31),0) -> 0.031566061
A10: Atorvastatin 20mg | B10: =VLOOKUP(A10, 'Raw Data '!B10:C509, 2, FALSE) -> Cardiovascular | C10: =LOOKUP(2,1/('Raw Data '!$B$2:$B$1000=A10), 'Raw Data '!$H$2:$H$1000) -> 13 | D10: =VLOOKUP(A10, 'Raw Data '!$B$2:$I$501, 8, FALSE) -> 20 | E10: =_xlfn.IFS(C10>D10, "Sufficient Stock", C10=0, "Out Of Stock", C10<=D10, "Reorder Soon" ) -> Reorder Soon | F10: =SUM(C10-D10) -> -7 | G10: =SUMIF(Table1[Medicine], Table2[[#This Row],[Medicine]],Table1[Quantity Sold]) -> 272 | H10: =VLOOKUP(A10,'Raw Data '!B10:E509, 4, FALSE) -> 2.89 | I10: =SUM(G10*H10) -> 786.08 | J10: =VLOOKUP(A10,'Raw Data '!B10:F509, 5, FALSE) -> 4.44 | K10: =SUM(G10*J10) -> 1207.68 | L10: =SUM(J10-H10) -> 1.55 | M10: =SUM(G10*L10) -> 421.6 | N10: =IFERROR(M10/K10, 0) -> 0.3490991 | O10: =SUM(C10*H10) -> 37.57 | P10: =MAX(D10-C10, 0) -> 7 | Q10: =IFERROR(K10/SUM($K$2:$K$31),0) -> 0.052782594
A11: Glimepiride 2mg | B11: =VLOOKUP(A11, 'Raw Data '!B11:C510, 2, FALSE) -> Diabetes | C11: =LOOKUP(2,1/('Raw Data '!$B$2:$B$1000=A11), 'Raw Data '!$H$2:$H$1000) -> 47 | D11: =VLOOKUP(A11, 'Raw Data '!$B$2:$I$501, 8, FALSE) -> 15 | E11: =_xlfn.IFS(C11>D11, "Sufficient Stock", C11=0, "Out Of Stock", C11<=D11, "Reorder Soon" ) -> Sufficient Stock | F11: =SUM(C11-D11) -> 32 | G11: =SUMIF(Table1[Medicine], Table2[[#This Row],[Medicine]],Table1[Quantity Sold]) -> 106 | H11: =VLOOKUP(A11,'Raw Data '!B11:E510, 4, FALSE) -> 2.17 | I11: =SUM(G11*H11) -> 230.02 | J11: =VLOOKUP(A11,'Raw Data '!B11:F510, 5, FALSE) -> 3.39 | K11: =SUM(G11*J11) -> 359.34 | L11: =SUM(J11-H11) -> 1.22 | M11: =SUM(G11*L11) -> 129.32 | N11: =IFERROR(M11/K11, 0) -> 0.35988201 | O11: =SUM(C11*H11) -> 101.99 | P11: =MAX(D11-C11, 0) -> 0 | Q11: =IFERROR(K11/SUM($K$2:$K$31),0) -> 0.015705234
A12: Paracetamol 500mg | B12: =VLOOKUP(A12, 'Raw Data '!B12:C511, 2, FALSE) -> Analgesic | C12: =LOOKUP(2,1/('Raw Data '!$B$2:$B$1000=A12), 'Raw Data '!$H$2:$H$1000) -> 62 | D12: =VLOOKUP(A12, 'Raw Data '!$B$2:$I$501, 8, FALSE) -> 35 | E12: =_xlfn.IFS(C12>D12, "Sufficient Stock", C12=0, "Out Of Stock", C12<=D12, "Reorder Soon" ) -> Sufficient Stock | F12: =SUM(C12-D12) -> 27 | G12: =SUMIF(Table1[Medicine], Table2[[#This Row],[Medicine]],Table1[Quantity Sold]) -> 902 | H12: =VLOOKUP(A12,'Raw Data '!B12:E511, 4, FALSE) -> 1.16 | I12: =SUM(G12*H12) -> 1046.32 | J12: =VLOOKUP(A12,'Raw Data '!B12:F511, 5, FALSE) -> 2.02 | K12: =SUM(G12*J12) -> 1822.04 | L12: =SUM(J12-H12) -> 0.86 | M12: =SUM(G12*L12) -> 775.72 | N12: =IFERROR(M12/K12, 0) -> 0.42574257 | O12: =SUM(C12*H12) -> 71.92 | P12: =MAX(D12-C12, 0) -> 0 | Q12: =IFERROR(K12/SUM($K$2:$K$31),0) -> 0.079633676
A13: Multivitamin Tablets | B13: =VLOOKUP(A13, 'Raw Data '!B13:C512, 2, FALSE) -> Vitamins | C13: =LOOKUP(2,1/('Raw Data '!$B$2:$B$1000=A13), 'Raw Data '!$H$2:$H$1000) -> 7 | D13: =VLOOKUP(A13, 'Raw Data '!$B$2:$I$501, 8, FALSE) -> 20 | E13: =_xlfn.IFS(C13>D13, "Sufficient Stock", C13=0, "Out Of Stock", C13<=D13, "Reorder Soon" ) -> Reorder Soon | F13: =SUM(C13-D13) -> -13 | G13: =SUMIF(Table1[Medicine], Table2[[#This Row],[Medicine]],Table1[Quantity Sold]) -> 239 | H13: =VLOOKUP(A13,'Raw Data '!B13:E512, 4, FALSE) -> 3.23 | I13: =SUM(G13*H13) -> 771.97 | J13: =VLOOKUP(A13,'Raw Data '!B13:F512, 5, FALSE) -> 5.02 | K13: =SUM(G13*J13) -> 1199.78 | L13: =SUM(J13-H13) -> 1.79 | M13: =SUM(G13*L13) -> 427.81 | N13: =IFERROR(M13/K13, 0) -> 0.35657371 | O13: =SUM(C13*H13) -> 22.61 | P13: =MAX(D13-C13, 0) -> 13 | Q13: =IFERROR(K13/SUM($K$2:$K$31),0) -> 0.052437318
... A31: Losartan 50mg | B31: =VLOOKUP(A31, 'Raw Data '!B31:C530, 2, FALSE) -> Cardiovascular | C31: =LOOKUP(2,1/('Raw Data '!$B$2:$B$1000=A31), 'Raw Data '!$H$2:$H$1000) -> 12 | D31: =VLOOKUP(A31, 'Raw Data '!$B$2:$I$501, 8, FALSE) -> 15 | E31: =_xlfn.IFS(C31>D31, "Sufficient Stock", C31=0, "Out Of Stock", C31<=D31, "Reorder Soon" ) -> Reorder Soon | F31: =SUM(C31-D31) -> -3 | G31: =SUMIF(Table1[Medicine], Table2[[#This Row],[Medicine]],Table1[Quantity Sold]) -> 156 | H31: =VLOOKUP(A31,'Raw Data '!B31:E530, 4, FALSE) -> 1.87 | I31: =SUM(G31*H31) -> 291.72 | J31: =VLOOKUP(A31,'Raw Data '!B31:F530, 5, FALSE) -> 3.11 | K31: =SUM(G31*J31) -> 485.16 | L31: =SUM(J31-H31) -> 1.24 | M31: =SUM(G31*L31) -> 193.44 | N31: =IFERROR(M31/K31, 0) -> 0.39871383 | O31: =SUM(C31*H31) -> 22.44 | P31: =MAX(D31-C31, 0) -> 3 | Q31: =IFERROR(K31/SUM($K$2:$K$31),0) -> 0.021204295

Sheet Dashboard
B1: PHARMACY INVENTORY & SALES DASHBOARD
B2: Total Sales Revenue | D2: Total Profit | F2: Inventory Value | H2: Total Units Sold | J2: Medicines Needing Reorder | L2: Sales Revenue By Category | N2: Top 5 Medicines By Quantity Sold | P2: Inventory Status
B3: =SUM('Inventory Sales'!K2:K31) -> 22880.27 | D3: =SUM('Inventory Sales'!M2:M31) -> 8518.56 | F3: =SUM('Inventory Sales'!O7:O31) -> 1644.59 | H3: =SUM('Inventory Sales'!G7:G31) -> 6216 | J3: =COUNTIF('Inventory Sales'!E2:E31,"Reorder Soon") + COUNTIF('Inventory Sales'!E2:E31,"Out Of Stock") -> 13 | L3: Category | M3: Revenue | N3: Medicine | O3: Quantity Sold | P3: Status | Q3: Number Of Medicine
L4: Antibiotic | M4: =SUMIF('Inventory Sales'!B5:B34,L4, 'Inventory Sales'!K5:K34) -> 3495.67 | N4: 1. Paracetamol 500mg | O4: 39 | P4: Sufficient Stock | Q4: =COUNTIF('Inventory Sales'!E2:E31, "Sufficient Stock") -> 17
L5: Respiratory | M5: =SUMIF('Inventory Sales'!B3:B32,L5, 'Inventory Sales'!K3:K32) -> 3014.43 | N5: 2. Vitamin C 500mg | O5: 37 | P5: Reorder Soon | Q5: =COUNTIF('Inventory Sales'!E2:E31,"Reorder Soon") -> 13
L6: Gastrointestinal | M6: =SUMIF('Inventory Sales'!B9:B38,L6, 'Inventory Sales'!K9:K38) -> 2958.07 | N6: 3. Omeprazole 20mg | O6: 34 | P6: Out Of Stock | Q6: =COUNTIF('Inventory Sales'!E7:E31,"Out Of Stock") -> 0
L7: Analgesic | M7: =SUMIF('Inventory Sales'!B4:B33,L7, 'Inventory Sales'!K4:K33) -> 2764.54 | N7: 4. Amlodipine 5mg | O7: 27
L8: Vitamins | M8: =SUMIF('Inventory Sales'!B2:B31,L8, 'Inventory Sales'!K2:K31) -> 2327.73 | N8: 5. Atorvastatin 20mg | O8: 24
L9: Ophthalmic | M9: =SUMIF('Inventory Sales'!B12:B41,L9, 'Inventory Sales'!K12:K41) -> 1069.75
L10: Dermatology | M10: =SUMIF('Inventory Sales'!B6:B35,L10, 'Inventory Sales'!K6:K35) -> 983.42
L11: Cardiovascular | M11: =SUMIF('Inventory Sales'!B11:B40,L11, 'Inventory Sales'!K11:K40) -> 782.2
L12: Diabetes | M12: =SUMIF('Inventory Sales'!B7:B36,L12, 'Inventory Sales'!K7:K36) -> 359.34
L13: Allergy | M13: =SUMIF('Inventory Sales'!B13:B42,L13, 'Inventory Sales'!K13:K42) -> 316.25
L14: Supplements | M14: =SUMIF('Inventory Sales'!B8:B37,L14, 'Inventory Sales'!K8:K37) -> 295.29
L15: Hydration | M15: =SUMIF('Inventory Sales'!B10:B39,L15, 'Inventory Sales'!K10:K39) -> 161.47

Sheet Pivot Table
A3: Row Labels | B3: Sum of Quantity Sold | D3: Row Labels | E3: Sum of Quantity Sold | G3: Row Labels | H3: Sum of Total Profit | J3: Row Labels | K3: Sum of Total Sales Revenue | M3: Row Labels | N3: Sum of Quantity Sold
A4: Allergy | B4: 457 | D4: PrimeMed Supplies | E4: 1433 | G4: Allergy | H4: 198.98 | J4: Allergy | K4: 609.27 | M4: 1. Paracetamol 500mg | N4: 39
A5: Analgesic | B5: 1654 | D5: HealthLine Distributors | E5: 1295 | G5: Analgesic | H5: 1385.14 | J5: Analgesic | K5: 3705.79 | M5: 2. Vitamin C 500mg | N5: 37
A6: Antibiotic | B6: 577 | D6: Nile Medical Trading | E6: 1116 | G6: Antibiotic | H6: 1315.37 | J6: Antibiotic | K6: 3495.67 | M6: 3. Omeprazole 20mg | N6: 34
A7: Cardiovascular | B7: 616 | D7: Medico Supply Co. | E7: 1088 | G7: Cardiovascular | H7: 716.56 | J7: Cardiovascular | K7: 1989.88 | M7: 4. Amlodipine 5mg | N7: 27
A8: Dermatology | B8: 327 | D8: GulfCare Medical | E8: 890 | G8: Dermatology | H8: 358.81 | J8: Dermatology | K8: 983.42 | M8: 5. Atorvastatin 20mg | N8: 24
A9: Diabetes | B9: 458 | D9: CarePlus Pharma | E9: 809 | G9: Diabetes | H9: 502.44 | J9: Diabetes | K9: 1351.98 | M9: Grand Total | N9: 161
A10: Gastrointestinal | B10: 953 | D10: Wellness Distribution | E10: 787 | G10: Gastrointestinal | H10: 1268.69 | J10: Gastrointestinal | K10: 3207.67
A11: Hydration | B11: 241 | D11: Grand Total | E11: 7418 | G11: Hydration | H11: 67.48 | J11: Hydration | K11: 161.47
A12: Ophthalmic | B12: 341 | G12: Ophthalmic | H12: 500.94 | J12: Ophthalmic | K12: 1358.17 | M12: Row Labels | N12: Sum of Number Of Medicine
A13: Respiratory | B13: 654 | G13: Respiratory | H13: 1132.75 | J13: Respiratory | K13: 3014.43 | M13: Sufficient Stock | N13: 23
A14: Supplements | B14: 318 | G14: Supplements | H14: 227.55 | J14: Supplements | K14: 674.79 | M14: Reorder Soon | N14: 7
A15: Vitamins | B15: 822 | G15: Vitamins | H15: 843.85 | J15: Vitamins | K15: 2327.73 | M15: Out Of Stock | N15: 0
A16: Grand Total | B16: 7418 | G16: Grand Total | H16: 8518.56 | J16: Grand Total | K16: 22880.27 | M16: Grand Total | N16: 30
